App_pkg/__init__.py
App_pkg/main.py
App_pkg/time_conversion.py
App_pkg/tests/__init__.py
App_pkg/tests/test_main.py
Covid19AlarmClock-0.0.1.dist-info/METADATA
Covid19AlarmClock-0.0.1.dist-info/WHEEL
Covid19AlarmClock-0.0.1.dist-info/license.md
Covid19AlarmClock-0.0.1.dist-info/top_level.txt
Covid19AlarmClock-0.0.1.dist-info/RECORD
