Metadata-Version: 2.1
Name: Covid19AlarmClock
Version: 0.0.1
Summary: COVID-19 Alarm Clock
Home-page: https://github.com/ElladanGE
Author: Duncan Watson
Author-email: dw574@exeter.ac.uk
License: UNKNOWN
Platform: UNKNOWN
Classifier: Programming Language :: Python :: 3
Classifier: License :: OSI Approved :: MIT License
Classifier: Operating System :: OS Independent
Requires-Python: >=3.6
